{
  "project_info": {
    "project_number": "532308756001",
    "project_id": "regenx-18",
    "storage_bucket": "regenx-18.firebasestorage.app"
  },
  "client": [
    {
      "client_info": {
        "mobilesdk_app_id": "1:532308756001:android:6f3486f21f1b2ef9808560",
        "android_client_info": {
          "package_name": "com.example.regenx"
        }
      },
      "oauth_client": [
        {
          "client_id": "942086189752-randomstringfromgoogle.apps.googleusercontent.com",
          "client_type": 1,
          "android_info": {
            "package_name": "com.example.regenx",
            "certificate_hash": "2CBC48A60A52D6703334A55C185F60BFAABF2987"
          }
        }
      ],
      "api_key": [
        {
          "current_key": "AIzaSyBZ8yAFmfPTBJKhuaZZvwQJPVi2hH5OT_E"
        }
      ],
      "services": {
        "appinvite_service": {
          "other_platform_oauth_client": []
        }
      }
    }
  ],
  "configuration_version": "1"
}